googleform/__init__.py
googleform/api.py
googleform/form.py
googleform/question.py
googleform/utils.py
googleform-0.0.1a1.dist-info/LICENSE
googleform-0.0.1a1.dist-info/METADATA
googleform-0.0.1a1.dist-info/WHEEL
googleform-0.0.1a1.dist-info/top_level.txt
googleform-0.0.1a1.dist-info/RECORD
