Metadata-Version: 2.1
Name: googleform
Version: 0.0.1a1
Summary: Submit Google Forms with magic
Home-page: https://github.com/joeltio/google-form-python
Author: Joel Tio
Author-email: joeltiojinhon@gmail.com
License: UNKNOWN
Platform: UNKNOWN
Classifier: Development Status :: 3 - Alpha
Classifier: Programming Language :: Python :: 3.5
Classifier: Programming Language :: Python :: 3.6
Classifier: Programming Language :: Python :: 3.7
Classifier: Intended Audience :: Developers
Classifier: Natural Language :: English
Classifier: License :: OSI Approved :: MIT License
Classifier: Operating System :: OS Independent
Requires-Dist: requests
Requires-Dist: lxml
